tlmr6400stats/__init__.py
tlmr6400stats/influx_logger.py
tlmr6400stats/log_states.py
tlmr6400stats/session.py
tlmr6400stats-1.0.0.dist-info/METADATA
tlmr6400stats-1.0.0.dist-info/WHEEL
tlmr6400stats-1.0.0.dist-info/top_level.txt
tlmr6400stats-1.0.0.dist-info/RECORD
